{
  "entries": [
    {
      "start": 121.84,
      "duration": 3.0,
      "text": "はい"
    },
    {
      "start": 165.08,
      "duration": 4.879,
      "text": "あうございますえおれでございますので"
    },
    {
      "start": 167.92,
      "duration": 3.84,
      "text": "議会運営委員会の協議会を始めさせて"
    },
    {
      "start": 169.959,
      "duration": 5.601,
      "text": "いただきますお手元の協議一項をご覧"
    },
    {
      "start": 171.76,
      "duration": 6.72,
      "text": "くださいえっと協議1番の協議会協議事項"
    },
    {
      "start": 175.56,
      "duration": 4.959,
      "text": "の1本日の進行予定について事務局からお"
    },
    {
      "start": 178.48,
      "duration": 4.8,
      "text": "願いいたします局長"
    },
    {
      "start": 180.519,
      "duration": 5.841,
      "text": "はいえそれではえっと本日のですね進行"
    },
    {
      "start": 183.28,
      "duration": 6.36,
      "text": "予定につきましてえお手元の進行予定表の"
    },
    {
      "start": 186.36,
      "duration": 6.799,
      "text": "各案ご覧いただきたいと思いますえ順の1"
    },
    {
      "start": 189.64,
      "duration": 6.519,
      "text": "番本会議先ほどあの会議宣告を今終了して"
    },
    {
      "start": 193.159,
      "duration": 6.881,
      "text": "おりますで2番の議会運営委員会及び同"
    },
    {
      "start": 196.159,
      "duration": 7.961,
      "text": "協議会ということでえ1番の市長送付案件"
    },
    {
      "start": 200.04,
      "duration": 7.32,
      "text": "の取り扱いについてえこちらはあのこの後"
    },
    {
      "start": 204.12,
      "duration": 6.6,
      "text": "ご説明します3番の本会議の2件のですね"
    },
    {
      "start": 207.36,
      "duration": 6.159,
      "text": "え取り扱いをここでお諮りをいただきます"
    },
    {
      "start": 210.72,
      "duration": 5.599,
      "text": "でえこちらの議会運営委員会同協議会が"
    },
    {
      "start": 213.519,
      "duration": 6.121,
      "text": "終了いたしましたら3番の本会議に移り"
    },
    {
      "start": 216.319,
      "duration": 8.401,
      "text": "ましてえ冒頭に議会運営委員長の委員長"
    },
    {
      "start": 219.64,
      "duration": 8.679,
      "text": "報告後にえ1番議案第22号え2番市長"
    },
    {
      "start": 224.72,
      "duration": 7.439,
      "text": "報告順にですねえ議事を進めていくという"
    },
    {
      "start": 228.319,
      "duration": 7.28,
      "text": "のが本日の進行の予定になります以上"
    },
    {
      "start": 232.159,
      "duration": 4.64,
      "text": "ですはいえ本日進行はそのような形になり"
    },
    {
      "start": 235.599,
      "duration": 4.881,
      "text": "ますが"
    },
    {
      "start": 236.799,
      "duration": 6.16,
      "text": "あその通りでよろしいでしょうか"
    },
    {
      "start": 240.48,
      "duration": 3.599,
      "text": "はいではあの委員会に入ってまいりますが"
    },
    {
      "start": 242.959,
      "duration": 7.041,
      "text": "大丈夫です"
    },
    {
      "start": 244.079,
      "duration": 5.921,
      "text": "かはいいいですかねはいいいですよねはい"
    },
    {
      "start": 250.92,
      "duration": 5.24,
      "text": "はいただ今から議会委員会の会議を開き"
    },
    {
      "start": 253.799,
      "duration": 4.641,
      "text": "ます直ちに議事に入ります当委員会に付託"
    },
    {
      "start": 256.16,
      "duration": 4.88,
      "text": "されております案件は議長の諮問事項1件"
    },
    {
      "start": 258.44,
      "duration": 4.64,
      "text": "であります議長からお手元に議会運営委員"
    },
    {
      "start": 261.04,
      "duration": 4.32,
      "text": "会協議事項が提示されておりますのでその"
    },
    {
      "start": 263.08,
      "duration": 4.679,
      "text": "順序に従って順次協議していきたいと思い"
    },
    {
      "start": 265.36,
      "duration": 4.88,
      "text": "ます議会運営に関する議長の諮問事項に"
    },
    {
      "start": 267.759,
      "duration": 5.081,
      "text": "ついてを議題といたします始めに協議事項"
    },
    {
      "start": 270.24,
      "duration": 4.64,
      "text": "括1市長送付案件の取り扱いについてを"
    },
    {
      "start": 272.84,
      "duration": 6.0,
      "text": "協議いたします部局から発言があればお"
    },
    {
      "start": 274.88,
      "duration": 7.4,
      "text": "願いいたしますはい総部長はいえ追加送付"
    },
    {
      "start": 278.84,
      "duration": 7.04,
      "text": "案件についてご報告いたしますえ追加送付"
    },
    {
      "start": 282.28,
      "duration": 6.8,
      "text": "案件として2月12日水曜日付けえ議案第"
    },
    {
      "start": 285.88,
      "duration": 7.599,
      "text": "22号令和6年度小金石一般会計法正予算"
    },
    {
      "start": 289.08,
      "duration": 6.88,
      "text": "第9回え2月14日金曜日付け視聴報告"
    },
    {
      "start": 293.479,
      "duration": 5.16,
      "text": "以上2件を送付させていただきましたので"
    },
    {
      "start": 295.96,
      "duration": 5.0,
      "text": "取り扱い方よろしくお願いいたしますはい"
    },
    {
      "start": 298.639,
      "duration": 4.161,
      "text": "取扱いについて長の問案が示されており"
    },
    {
      "start": 300.96,
      "duration": 4.6,
      "text": "ますので議長から説明をお願いいたします"
    },
    {
      "start": 302.8,
      "duration": 6.88,
      "text": "はいえ事務局から説明いたしますはい"
    },
    {
      "start": 305.56,
      "duration": 8.28,
      "text": "局長はいえ議案第22号につきましては"
    },
    {
      "start": 309.68,
      "duration": 7.84,
      "text": "本日の本会議に上帝し説明質疑後予算特別"
    },
    {
      "start": 313.84,
      "duration": 6.6,
      "text": "委員会に付託市長報告につきましては本日"
    },
    {
      "start": 317.52,
      "duration": 6.32,
      "text": "の本会議で所定の手続きを取りたいという"
    },
    {
      "start": 320.44,
      "duration": 5.8,
      "text": "のが議長の諮問案でございますはい議長"
    },
    {
      "start": 323.84,
      "duration": 8.32,
      "text": "及び事務局の説明は終わりましたご意見ご"
    },
    {
      "start": 326.24,
      "duration": 9.88,
      "text": "質疑とございますかはい委員えっと視聴"
    },
    {
      "start": 332.16,
      "duration": 8.319,
      "text": "報告なんですがあの今回の視聴報告はあの"
    },
    {
      "start": 336.12,
      "duration": 8.0,
      "text": "主張公約を撤回するま重大な内容があの"
    },
    {
      "start": 340.479,
      "duration": 7.16,
      "text": "示されておりますあの前回の市長選挙は"
    },
    {
      "start": 344.12,
      "duration": 6.919,
      "text": "ですねあの荒れの1つではなくこの都市"
    },
    {
      "start": 347.639,
      "duration": 6.161,
      "text": "計画道路の問題っていうのはま主要な争点"
    },
    {
      "start": 351.039,
      "duration": 5.681,
      "text": "の1つだったと思うんですねで今の市来"
    },
    {
      "start": 353.8,
      "duration": 5.399,
      "text": "市長に要するにその期待を持ってですね"
    },
    {
      "start": 356.72,
      "duration": 3.44,
      "text": "あの投票された方も儲かったというふに"
    },
    {
      "start": 359.199,
      "duration": 4.081,
      "text": "思います"
    },
    {
      "start": 360.16,
      "duration": 5.56,
      "text": "まそれがですねこういう形であの撤回され"
    },
    {
      "start": 363.28,
      "duration": 5.6,
      "text": "るっていうことは非常にま遺憾だという風"
    },
    {
      "start": 365.72,
      "duration": 6.12,
      "text": "に思っておりましてあのこれからま主張"
    },
    {
      "start": 368.88,
      "duration": 7.12,
      "text": "報告っていうことなんですがやっぱり私は"
    },
    {
      "start": 371.84,
      "duration": 7.799,
      "text": "ですね冒頭にあのその公約に対するその"
    },
    {
      "start": 376.0,
      "duration": 6.759,
      "text": "自らの責任とあの市民に対する謝罪はです"
    },
    {
      "start": 379.639,
      "duration": 5.96,
      "text": "ね少なくともきちんと行わなければまいけ"
    },
    {
      "start": 382.759,
      "duration": 6.961,
      "text": "ないという風に考えておりますしえっと"
    },
    {
      "start": 385.599,
      "duration": 6.761,
      "text": "今朝あの市民団体6団体からあの市長"
    },
    {
      "start": 389.72,
      "duration": 5.64,
      "text": "申し入れがあって私たちの会派にもあの"
    },
    {
      "start": 392.36,
      "duration": 8.36,
      "text": "申し入れ者が配られたんですがあの市民"
    },
    {
      "start": 395.36,
      "duration": 7.44,
      "text": "説明会をあの要するに行った上であの東京"
    },
    {
      "start": 400.72,
      "duration": 5.199,
      "text": "都に要望書を出してもらいたいっていう"
    },
    {
      "start": 402.8,
      "duration": 6.44,
      "text": "ことで市民説明会を行うっていうことも"
    },
    {
      "start": 405.919,
      "duration": 6.441,
      "text": "当然だと思うんですが主張報告の中には"
    },
    {
      "start": 409.24,
      "duration": 6.519,
      "text": "ですねその要するにその市民への説明あの"
    },
    {
      "start": 412.36,
      "duration": 6.32,
      "text": "市民への要するに謝罪と説明っていうのは"
    },
    {
      "start": 415.759,
      "duration": 5.921,
      "text": "一切触れられていないとまいう中身になっ"
    },
    {
      "start": 418.68,
      "duration": 5.32,
      "text": "てましてですからこのままですねじゃあ"
    },
    {
      "start": 421.68,
      "duration": 6.32,
      "text": "市長報告っていうことで市長からの報告を"
    },
    {
      "start": 424.0,
      "duration": 6.56,
      "text": "受けてま質疑に入るとまいう形には私はね"
    },
    {
      "start": 428.0,
      "duration": 6.199,
      "text": "ならないんじゃないかなっていう風にあと"
    },
    {
      "start": 430.56,
      "duration": 7.479,
      "text": "いう風には考えておりますでそれであの全"
    },
    {
      "start": 434.199,
      "duration": 7.081,
      "text": "西岡市長はですね少なくとも要するにあの"
    },
    {
      "start": 438.039,
      "duration": 6.16,
      "text": "市民の理解が得られない道路は尽せないと"
    },
    {
      "start": 441.28,
      "duration": 5.639,
      "text": "市民合意をやっぱりね重視されていたわけ"
    },
    {
      "start": 444.199,
      "duration": 5.72,
      "text": "でそれからも要するに大きく交代するよう"
    },
    {
      "start": 446.919,
      "duration": 6.441,
      "text": "中身になってますからま謝罪と市民説明"
    },
    {
      "start": 449.919,
      "duration": 6.361,
      "text": "っていうのはあのどうするのかあの明確に"
    },
    {
      "start": 453.36,
      "duration": 6.88,
      "text": "するべきだと思っておりますであの4社教"
    },
    {
      "start": 456.28,
      "duration": 7.599,
      "text": "のですねあの話を聞いたところえっと視聴"
    },
    {
      "start": 460.24,
      "duration": 7.519,
      "text": "報告終わった後にですねあの市長から何ら"
    },
    {
      "start": 463.879,
      "duration": 7.121,
      "text": "か発言があの行われるとまいう風に聞い"
    },
    {
      "start": 467.759,
      "duration": 6.761,
      "text": "てるんですがその発言がどういう発言なの"
    },
    {
      "start": 471.0,
      "duration": 6.08,
      "text": "かあのその中身も分からずにですね"
    },
    {
      "start": 474.52,
      "duration": 5.84,
      "text": "ちょっと僕らこのまま祝しと進めるわけに"
    },
    {
      "start": 477.08,
      "duration": 7.32,
      "text": "はいかないという風に考えておりますて"
    },
    {
      "start": 480.36,
      "duration": 6.32,
      "text": "あのま冒頭私はま謝罪市民説明どうするの"
    },
    {
      "start": 484.4,
      "duration": 6.28,
      "text": "かっていう見解を求めたいと思っており"
    },
    {
      "start": 486.68,
      "duration": 7.12,
      "text": "ますがあの市長が発言されるっていうよう"
    },
    {
      "start": 490.68,
      "duration": 6.44,
      "text": "な内容についてはちょっとね事前に明らか"
    },
    {
      "start": 493.8,
      "duration": 7.359,
      "text": "にしといてもらわないとあのどういう中身"
    },
    {
      "start": 497.12,
      "duration": 7.12,
      "text": "を発言されるのかあの要するに市長報告が"
    },
    {
      "start": 501.159,
      "duration": 5.401,
      "text": "終わった後に発言されるわけですよねま"
    },
    {
      "start": 504.24,
      "duration": 5.799,
      "text": "本来まどういう中身なのかよくわかんない"
    },
    {
      "start": 506.56,
      "duration": 7.039,
      "text": "ですけどま謝罪みたいな形になってくると"
    },
    {
      "start": 510.039,
      "duration": 6.961,
      "text": "本来は謝罪があってあの視聴報告っていう"
    },
    {
      "start": 513.599,
      "duration": 6.32,
      "text": "形に本来はなるべきだと思うんですけどだ"
    },
    {
      "start": 517.0,
      "duration": 5.959,
      "text": "からそのその要するに視聴あの発言につい"
    },
    {
      "start": 519.919,
      "duration": 5.001,
      "text": "てはですねちょっと議運でもあの内容を"
    },
    {
      "start": 522.959,
      "duration": 4.401,
      "text": "確認する必要があるんではないかなって"
    },
    {
      "start": 524.92,
      "duration": 5.359,
      "text": "いう風に思うのでちょっと委員長からも"
    },
    {
      "start": 527.36,
      "duration": 4.8,
      "text": "是非お取り計いお願いしたいとまいうこと"
    },
    {
      "start": 530.279,
      "duration": 4.721,
      "text": "はちょっと申し上げておきたいと思います"
    },
    {
      "start": 532.16,
      "duration": 4.56,
      "text": "以上ですはいこの件について他にござい"
    },
    {
      "start": 535.0,
      "duration": 6.64,
      "text": "ますかはい片山副委"
    },
    {
      "start": 536.72,
      "duration": 7.52,
      "text": "長あのからりましたけれどもあの主張報告"
    },
    {
      "start": 541.64,
      "duration": 5.48,
      "text": "の後に謝罪っていうようなねあの発言をし"
    },
    {
      "start": 544.24,
      "duration": 5.32,
      "text": "たいというようなことがなんかあるような"
    },
    {
      "start": 547.12,
      "duration": 5.48,
      "text": "んですがちょっとですねそれありえないん"
    },
    {
      "start": 549.56,
      "duration": 5.519,
      "text": "じゃないかなとあのそれでだったら私です"
    },
    {
      "start": 552.6,
      "duration": 6.12,
      "text": "ねこの視聴報告をきちんとあの作り直して"
    },
    {
      "start": 555.079,
      "duration": 7.2,
      "text": "欲しいんですよあのこの主張報告の中で"
    },
    {
      "start": 558.72,
      "duration": 5.92,
      "text": "本来は謝罪なりですねがあるべきですしま"
    },
    {
      "start": 562.279,
      "duration": 5.081,
      "text": "そもそもあの公約を撤回するような視聴"
    },
    {
      "start": 564.64,
      "duration": 4.759,
      "text": "報告をいきなりこうやって議会にねポンと"
    },
    {
      "start": 567.36,
      "duration": 4.8,
      "text": "出してくるなんてことはありえないですよ"
    },
    {
      "start": 569.399,
      "duration": 5.161,
      "text": "市民何も説明なくて一体どういうことなの"
    },
    {
      "start": 572.16,
      "duration": 5.239,
      "text": "かと思いますねまこういったあの謝罪をし"
    },
    {
      "start": 574.56,
      "duration": 5.16,
      "text": "たいというんであれば改めてこの主張報告"
    },
    {
      "start": 577.399,
      "duration": 4.321,
      "text": "は撤回してもう1度ですねきちんとした"
    },
    {
      "start": 579.72,
      "duration": 5.08,
      "text": "ものを作り直すというようなことを私は"
    },
    {
      "start": 581.72,
      "duration": 5.119,
      "text": "求めたいと思いますはい他にこの件ござい"
    },
    {
      "start": 584.8,
      "duration": 5.64,
      "text": "ますかはい安田"
    },
    {
      "start": 586.839,
      "duration": 6.481,
      "text": "委員はい今回の視聴報告ですけれどもま"
    },
    {
      "start": 590.44,
      "duration": 6.92,
      "text": "公約違反は明らかでありますえこの中には"
    },
    {
      "start": 593.32,
      "duration": 8.639,
      "text": "え市名の説明も何も含まれておりませんえ"
    },
    {
      "start": 597.36,
      "duration": 7.32,
      "text": "今まではもあの水上委員や片山委員からも"
    },
    {
      "start": 601.959,
      "duration": 6.361,
      "text": "発言がありました通り私も同意いたします"
    },
    {
      "start": 604.68,
      "duration": 7.279,
      "text": "えそれをなしにえ市民への説明お詫びも"
    },
    {
      "start": 608.32,
      "duration": 7.44,
      "text": "なしにこのまま視聴報告を認めるわけには"
    },
    {
      "start": 611.959,
      "duration": 6.601,
      "text": "いかないとえ申し上げておきますはい他に"
    },
    {
      "start": 615.76,
      "duration": 7.04,
      "text": "ございますかはい"
    },
    {
      "start": 618.56,
      "duration": 6.68,
      "text": "水谷はいえっと市長報告の後のえっと市長"
    },
    {
      "start": 622.8,
      "duration": 5.039,
      "text": "の発言の内容が分からないということで"
    },
    {
      "start": 625.24,
      "duration": 7.48,
      "text": "あのそれを説明を求めるべきというご意見"
    },
    {
      "start": 627.839,
      "duration": 7.081,
      "text": "が今出ておりますでえっと視聴報告の中に"
    },
    {
      "start": 632.72,
      "duration": 5.559,
      "text": "その謝罪も含めるべきだというあのご意見"
    },
    {
      "start": 634.92,
      "duration": 6.44,
      "text": "も今出たと思っていますでえっと市長報告"
    },
    {
      "start": 638.279,
      "duration": 5.281,
      "text": "をもう1度撤回してあの作成し直すべきだ"
    },
    {
      "start": 641.36,
      "duration": 7.68,
      "text": "というご意見もあったのと受け止めてるん"
    },
    {
      "start": 643.56,
      "duration": 9.44,
      "text": "ですがあの視聴報告の内容は総合的な判断"
    },
    {
      "start": 649.04,
      "duration": 7.0,
      "text": "という風になっていましてでその総合的"
    },
    {
      "start": 653.0,
      "duration": 5.2,
      "text": "判断をまなぜしたのかっていうま市民の"
    },
    {
      "start": 656.04,
      "duration": 5.0,
      "text": "説明が必要なのはもちろんのことでして"
    },
    {
      "start": 658.2,
      "duration": 5.04,
      "text": "謝罪もあのというの必要だと思います市民"
    },
    {
      "start": 661.04,
      "duration": 5.039,
      "text": "説明会についてのコメントも必要だと思う"
    },
    {
      "start": 663.24,
      "duration": 5.96,
      "text": "んですがその総合的判断の中身というもの"
    },
    {
      "start": 666.079,
      "duration": 5.0,
      "text": "とそのそれに対するま市長の政治的なあの"
    },
    {
      "start": 669.2,
      "duration": 4.6,
      "text": "説明責任とかそういったものというのは"
    },
    {
      "start": 671.079,
      "duration": 6.161,
      "text": "少し内容が異なると思いますので報告の"
    },
    {
      "start": 673.8,
      "duration": 5.159,
      "text": "内容とその謝罪をもう1度1度にしてあの"
    },
    {
      "start": 677.24,
      "duration": 3.8,
      "text": "出し直しべきということについては"
    },
    {
      "start": 678.959,
      "duration": 6.761,
      "text": "ちょっと違うのではないかなと思い"
    },
    {
      "start": 681.04,
      "duration": 10.479,
      "text": "ますはい他にございますかはい"
    },
    {
      "start": 685.72,
      "duration": 9.64,
      "text": "小あの今日はあの備の検証に対するその"
    },
    {
      "start": 691.519,
      "duration": 6.201,
      "text": "総合的判断を主張が報告をするという場で"
    },
    {
      "start": 695.36,
      "duration": 5.76,
      "text": "ありますのでま今出たような意見っていう"
    },
    {
      "start": 697.72,
      "duration": 5.6,
      "text": "のはまさにそこを質疑の中でですねあの"
    },
    {
      "start": 701.12,
      "duration": 4.8,
      "text": "明らかにしていくんじゃないかなと思って"
    },
    {
      "start": 703.32,
      "duration": 5.639,
      "text": "おりまして多くの防長者の方も"
    },
    {
      "start": 705.92,
      "duration": 5.88,
      "text": "いらっしゃいますのでえ速やかにですね"
    },
    {
      "start": 708.959,
      "duration": 5.201,
      "text": "視聴報告へ入っていくべきではないかなと"
    },
    {
      "start": 711.8,
      "duration": 9.039,
      "text": "思っており"
    },
    {
      "start": 714.16,
      "duration": 9.239,
      "text": "ますはいはい他にございますかはい"
    },
    {
      "start": 720.839,
      "duration": 4.721,
      "text": "えっと今皆様の意見をちゃんと聞かせて"
    },
    {
      "start": 723.399,
      "duration": 5.161,
      "text": "いただきましたけれどもやはりあの私も"
    },
    {
      "start": 725.56,
      "duration": 5.279,
      "text": "小部さんと同じ意見でございましてあ"
    },
    {
      "start": 728.56,
      "duration": 4.36,
      "text": "まず本当にたくさんの方も待っ"
    },
    {
      "start": 730.839,
      "duration": 4.0,
      "text": "てらっしゃることもありますので速やかに"
    },
    {
      "start": 732.92,
      "duration": 4.8,
      "text": "事情の方進めていくべきでないかと思って"
    },
    {
      "start": 734.839,
      "duration": 6.44,
      "text": "おります以上ですはいはい片山副委員長"
    },
    {
      "start": 737.72,
      "duration": 6.32,
      "text": "はいえっとですねあのま色々意見はあるか"
    },
    {
      "start": 741.279,
      "duration": 5.401,
      "text": "もしれませんけれどもただですねこの発言"
    },
    {
      "start": 744.04,
      "duration": 5.799,
      "text": "をしたいというのはこ異例なわけですよで"
    },
    {
      "start": 746.68,
      "duration": 6.04,
      "text": "本来はこの主張報告のあののところにです"
    },
    {
      "start": 749.839,
      "duration": 5.081,
      "text": "ねあの先ほどからあの三上さん最初から"
    },
    {
      "start": 752.72,
      "duration": 4.52,
      "text": "おっしゃってるようにまきちんと謝罪が"
    },
    {
      "start": 754.92,
      "duration": 4.88,
      "text": "含められてるということであればそのよう"
    },
    {
      "start": 757.24,
      "duration": 4.839,
      "text": "な付け足しのようなですね謝罪をしたいと"
    },
    {
      "start": 759.8,
      "duration": 4.839,
      "text": "いうな発言を求めるなんてことはないわけ"
    },
    {
      "start": 762.079,
      "duration": 4.56,
      "text": "ですよだけどそういったね発言をしたいと"
    },
    {
      "start": 764.639,
      "duration": 4.041,
      "text": "いうんであればどういう発言するのかって"
    },
    {
      "start": 766.639,
      "duration": 4.041,
      "text": "やっぱり内容を出していただかないとで"
    },
    {
      "start": 768.68,
      "duration": 5.56,
      "text": "ないとその発言をしていいかどうかも認め"
    },
    {
      "start": 770.68,
      "duration": 6.959,
      "text": "られませんどのような発言をするのかこの"
    },
    {
      "start": 774.24,
      "duration": 5.76,
      "text": "あの視誰に対しての謝罪なのか市民に対し"
    },
    {
      "start": 777.639,
      "duration": 5.76,
      "text": "てなのか議会に対してなのか分かりません"
    },
    {
      "start": 780.0,
      "duration": 6.88,
      "text": "けれどもそういった内容そしてまたまこの"
    },
    {
      "start": 783.399,
      "duration": 7.0,
      "text": "ねあの例えばま公約違反なわけですからま"
    },
    {
      "start": 786.88,
      "duration": 5.68,
      "text": "自分の職をねじして謝罪したいということ"
    },
    {
      "start": 790.399,
      "duration": 4.641,
      "text": "かもしれませんよねまそういったあの重大"
    },
    {
      "start": 792.56,
      "duration": 5.8,
      "text": "な発言かもしれませんのでとにかく中身を"
    },
    {
      "start": 795.04,
      "duration": 5.44,
      "text": "確認したいですだから中身を確認してから"
    },
    {
      "start": 798.36,
      "duration": 3.68,
      "text": "あのこの後ですね議事をあの進めて"
    },
    {
      "start": 800.48,
      "duration": 4.68,
      "text": "いただきたいと思いますのでよろしくお"
    },
    {
      "start": 802.04,
      "duration": 5.84,
      "text": "願いいたしますはい小林委ちょっとあの"
    },
    {
      "start": 805.16,
      "duration": 6.4,
      "text": "どこまでがあの真実なのかちょっと分から"
    },
    {
      "start": 807.88,
      "duration": 8.36,
      "text": "ない質疑でえっと市長から謝罪発言をし"
    },
    {
      "start": 811.56,
      "duration": 6.519,
      "text": "たいというう何要請があったの謝罪の発言"
    },
    {
      "start": 816.24,
      "duration": 3.599,
      "text": "をしたいっていう要請があったんですか"
    },
    {
      "start": 818.079,
      "duration": 4.961,
      "text": "正確に言ってもらっていいですか謝罪の"
    },
    {
      "start": 819.839,
      "duration": 5.841,
      "text": "発言をここに今日したいっていうことだと"
    },
    {
      "start": 823.04,
      "duration": 5.08,
      "text": "あの我々もその内容をちゃんと確認し"
    },
    {
      "start": 825.68,
      "duration": 5.159,
      "text": "なきゃいけないですよねあの視聴報告が"
    },
    {
      "start": 828.12,
      "duration": 6.04,
      "text": "あってその視聴報告の内容を左右するよう"
    },
    {
      "start": 830.839,
      "duration": 6.12,
      "text": "な発言があるとなればうんだから誰がどう"
    },
    {
      "start": 834.16,
      "duration": 5.96,
      "text": "いうことを今要請さその議論をしてるのか"
    },
    {
      "start": 836.959,
      "duration": 6.0,
      "text": "がちょっとあの言ってることがよくわかん"
    },
    {
      "start": 840.12,
      "duration": 5.079,
      "text": "ない4者で話してることもですねあの我々"
    },
    {
      "start": 842.959,
      "duration": 5.12,
      "text": "には正確に伝わってませんのであの"
    },
    {
      "start": 845.199,
      "duration": 7.041,
      "text": "ちょっと整理してくださいはいでその点に"
    },
    {
      "start": 848.079,
      "duration": 7.641,
      "text": "ついて議長から特長からではい議長全体に"
    },
    {
      "start": 852.24,
      "duration": 5.959,
      "text": "え全体のやり取りにあのついてはあの局長"
    },
    {
      "start": 855.72,
      "duration": 6.08,
      "text": "が色々あの詳しく知てますので局長の方"
    },
    {
      "start": 858.199,
      "duration": 3.601,
      "text": "から説明お願いしますはい"
    },
    {
      "start": 864.16,
      "duration": 7.88,
      "text": "局長はいえっとじゃまずですね昨日あの長"
    },
    {
      "start": 867.6,
      "duration": 8.359,
      "text": "から連絡がありますしてえまそのえ視聴"
    },
    {
      "start": 872.04,
      "duration": 6.599,
      "text": "発言あ主張報告終わった後にえもう1回手"
    },
    {
      "start": 875.959,
      "duration": 4.8,
      "text": "を上げてえ発言をしたいということで"
    },
    {
      "start": 878.639,
      "duration": 4.921,
      "text": "おっしゃってましたのでえそれについてま"
    },
    {
      "start": 880.759,
      "duration": 3.88,
      "text": "局長とも相談しながらえあそういうことで"
    },
    {
      "start": 883.56,
      "duration": 4.8,
      "text": "あれば"
    },
    {
      "start": 884.639,
      "duration": 5.401,
      "text": "あのまあの供給運動の中でねえ図ってやっ"
    },
    {
      "start": 888.36,
      "duration": 5.44,
      "text": "ていくことになるということで見解をし"
    },
    {
      "start": 890.04,
      "duration": 7.28,
      "text": "ましたとことでありますはい小林ですはい"
    },
    {
      "start": 893.8,
      "duration": 6.88,
      "text": "今ま今の議長がご説明されたような内容で"
    },
    {
      "start": 897.32,
      "duration": 6.04,
      "text": "あればですねま本来そのわざわざその釘"
    },
    {
      "start": 900.68,
      "duration": 7.04,
      "text": "っていう話じゃなくてあのこの主張の報告"
    },
    {
      "start": 903.36,
      "duration": 7.12,
      "text": "をま読み上げるその中にね"
    },
    {
      "start": 907.72,
      "duration": 4.479,
      "text": "あの最後の言葉として付け加え"
    },
    {
      "start": 910.48,
      "duration": 4.039,
      "text": "るってことは今までもあったような気がし"
    },
    {
      "start": 912.199,
      "duration": 5.64,
      "text": "ますのでねまその範囲でいいのかなと思い"
    },
    {
      "start": 914.519,
      "duration": 6.921,
      "text": "ますもちろんその内容を聞いたない上で"
    },
    {
      "start": 917.839,
      "duration": 5.961,
      "text": "あの私も何度も手上げてねそれ文章であの"
    },
    {
      "start": 921.44,
      "duration": 4.88,
      "text": "出してくれってことはもう毎回やってきて"
    },
    {
      "start": 923.8,
      "duration": 4.88,
      "text": "ますのであの私としてはその内容を聞いて"
    },
    {
      "start": 926.32,
      "duration": 3.8,
      "text": "ねあの判断したいなというところであり"
    },
    {
      "start": 928.68,
      "duration": 6.159,
      "text": "ます"
    },
    {
      "start": 930.12,
      "duration": 7.719,
      "text": "はいはい水上委員それであの今回の視聴"
    },
    {
      "start": 934.839,
      "duration": 6.12,
      "text": "報告の中身はですねちょっと皆さんも考え"
    },
    {
      "start": 937.839,
      "duration": 6.761,
      "text": "てもらいたいんですけどあの前回の市長"
    },
    {
      "start": 940.959,
      "duration": 6.841,
      "text": "選挙で公約したことが覆るって中身なん"
    },
    {
      "start": 944.6,
      "duration": 5.96,
      "text": "ですねその重大性を是非ね理解してもらい"
    },
    {
      "start": 947.8,
      "duration": 7.159,
      "text": "たいと思うんですよだそういうものをこれ"
    },
    {
      "start": 950.56,
      "duration": 6.36,
      "text": "から視聴報告として扱う上であの議会とし"
    },
    {
      "start": 954.959,
      "duration": 6.281,
      "text": "てどういう対応をすべきなのかっていう"
    },
    {
      "start": 956.92,
      "duration": 8.159,
      "text": "ことでで後で市長報告の後で市長が発言"
    },
    {
      "start": 961.24,
      "duration": 6.92,
      "text": "するとで何を発言するかも分からないとあ"
    },
    {
      "start": 965.079,
      "duration": 5.961,
      "text": "いう形になってるわけですよね今で私は"
    },
    {
      "start": 968.16,
      "duration": 4.72,
      "text": "やっぱり少なくとも公約撤回したわけだ"
    },
    {
      "start": 971.04,
      "duration": 5.52,
      "text": "から市長報告っていうのはなんか市長が"
    },
    {
      "start": 972.88,
      "duration": 6.56,
      "text": "やるものであの政治的な立場となんか別々"
    },
    {
      "start": 976.56,
      "duration": 6.399,
      "text": "なんだって話もあったけれども市長は"
    },
    {
      "start": 979.44,
      "duration": 6.16,
      "text": "やっぱり市長として政治責任もあるしあの"
    },
    {
      "start": 982.959,
      "duration": 5.521,
      "text": "行政のトップとしての責任もあると思い"
    },
    {
      "start": 985.6,
      "duration": 3.919,
      "text": "ますがやっぱりね政治責任問われると思う"
    },
    {
      "start": 988.48,
      "duration": 3.44,
      "text": "んですよ"
    },
    {
      "start": 989.519,
      "duration": 5.041,
      "text": "ですからそういうものを扱う時にですね"
    },
    {
      "start": 991.92,
      "duration": 5.279,
      "text": "何かよく分からない発言が後でされ"
    },
    {
      "start": 994.56,
      "duration": 5.48,
      "text": "るっていうことについてはあの議会として"
    },
    {
      "start": 997.199,
      "duration": 6.44,
      "text": "やっぱりねどういう風な発言されるのか"
    },
    {
      "start": 1000.04,
      "duration": 6.68,
      "text": "あのその中身については一応ね確認した上"
    },
    {
      "start": 1003.639,
      "duration": 5.44,
      "text": "で入っていかないとあのちょっとスムーズ"
    },
    {
      "start": 1006.72,
      "duration": 6.119,
      "text": "な議事運営にもならないっていう風に思っ"
    },
    {
      "start": 1009.079,
      "duration": 6.88,
      "text": "てますで私は最初あの飲めましたけれども"
    },
    {
      "start": 1012.839,
      "duration": 6.401,
      "text": "やっぱりねちゃんとした謝罪がないとあの"
    },
    {
      "start": 1015.959,
      "duration": 6.44,
      "text": "市民に対して公約だったわけだから市民の"
    },
    {
      "start": 1019.24,
      "duration": 7.12,
      "text": "約束ですよねでそれがやっぱり保護にさ"
    },
    {
      "start": 1022.399,
      "duration": 7.28,
      "text": "れるわけだからそれに対する自らの責任が"
    },
    {
      "start": 1026.36,
      "duration": 5.64,
      "text": "あの全く述べられないであの主張報告に"
    },
    {
      "start": 1029.679,
      "duration": 5.28,
      "text": "そのまま入ってくっていうことにはなら"
    },
    {
      "start": 1032.0,
      "duration": 5.799,
      "text": "ないしその後の発言がどういう発言なのか"
    },
    {
      "start": 1034.959,
      "duration": 6.041,
      "text": "わからないですけどあのそれもよくわかん"
    },
    {
      "start": 1037.799,
      "duration": 5.801,
      "text": "ないままちょっとねあの私はあの議会運営"
    },
    {
      "start": 1041.0,
      "duration": 4.839,
      "text": "委員会としてこのままあじゃいいですよっ"
    },
    {
      "start": 1043.6,
      "duration": 4.92,
      "text": "てことにはならないとまいうことだと思い"
    },
    {
      "start": 1045.839,
      "duration": 3.601,
      "text": "ますので少なくともどういう発言されるの"
    },
    {
      "start": 1048.52,
      "duration": 4.279,
      "text": "か"
    },
    {
      "start": 1049.44,
      "duration": 5.359,
      "text": "あのその内容についてはあの別にそのね"
    },
    {
      "start": 1052.799,
      "duration": 5.481,
      "text": "隠すことじゃないじゃないですか事前に"
    },
    {
      "start": 1054.799,
      "duration": 5.88,
      "text": "主張方向だって出てるわけだしね特別発言"
    },
    {
      "start": 1058.28,
      "duration": 5.6,
      "text": "したいてことであればどういう発言される"
    },
    {
      "start": 1060.679,
      "duration": 5.201,
      "text": "のかって別に隠すことでもないので是非"
    },
    {
      "start": 1063.88,
      "duration": 3.96,
      "text": "それはね明らかにしていただきたいなと"
    },
    {
      "start": 1065.88,
      "duration": 5.12,
      "text": "いう風に思うんですがいかがでしょうか"
    },
    {
      "start": 1067.84,
      "duration": 5.839,
      "text": "はいはい片山副委員長はいあのすでにです"
    },
    {
      "start": 1071.0,
      "duration": 4.799,
      "text": "ね4社の時にその話はなってるのであの"
    },
    {
      "start": 1073.679,
      "duration": 4.161,
      "text": "伝えてると思います市長の方にそういった"
    },
    {
      "start": 1075.799,
      "duration": 4.641,
      "text": "発言内容を出してくださいということに"
    },
    {
      "start": 1077.84,
      "duration": 4.92,
      "text": "ついてはもうあの部長を通じてですね伝え"
    },
    {
      "start": 1080.44,
      "duration": 4.2,
      "text": "てるはずですのでちらの方お待ちしてます"
    },
    {
      "start": 1082.76,
      "duration": 4.96,
      "text": "ので是非とも果たしていただきたいと思い"
    },
    {
      "start": 1084.64,
      "duration": 4.919,
      "text": "ますはいまあの発言の詳細については"
    },
    {
      "start": 1087.72,
      "duration": 5.959,
      "text": "私たちは承知はしておりませんけどその点"
    },
    {
      "start": 1089.559,
      "duration": 7.641,
      "text": "総務部長何か聞いてますかはい総務部長"
    },
    {
      "start": 1093.679,
      "duration": 7.561,
      "text": "はいあの視聴報告をさせていただいた後に"
    },
    {
      "start": 1097.2,
      "duration": 6.959,
      "text": "ですね一定あの市長の方からご発言をされ"
    },
    {
      "start": 1101.24,
      "duration": 6.439,
      "text": "たいということは聞いてございますただ"
    },
    {
      "start": 1104.159,
      "duration": 6.76,
      "text": "あのここでされる市長のご発言の内容に"
    },
    {
      "start": 1107.679,
      "duration": 7.161,
      "text": "ついてえ私の方でえまだ確認しきれている"
    },
    {
      "start": 1110.919,
      "duration": 6.961,
      "text": "という状況ではございませんえあらかじめ"
    },
    {
      "start": 1114.84,
      "duration": 5.68,
      "text": "議会の方でそのご確認後ということであれ"
    },
    {
      "start": 1117.88,
      "duration": 5.36,
      "text": "ば市長の方に私の方で確認してまいります"
    },
    {
      "start": 1120.52,
      "duration": 4.88,
      "text": "のでその際は今少し時間をいただきたいと"
    },
    {
      "start": 1123.24,
      "duration": 6.28,
      "text": "思います"
    },
    {
      "start": 1125.4,
      "duration": 7.68,
      "text": "はいということでではえはい小林"
    },
    {
      "start": 1129.52,
      "duration": 7.0,
      "text": "市議まやり方としてねその今までやってた"
    },
    {
      "start": 1133.08,
      "duration": 8.36,
      "text": "のは議運でそこまで言ってじゃあその配っ"
    },
    {
      "start": 1136.52,
      "duration": 7.72,
      "text": "た状態でええ視聴報告が始まりその発言が"
    },
    {
      "start": 1141.44,
      "duration": 6.599,
      "text": "ありっていうことはやりましたね喋った後"
    },
    {
      "start": 1144.24,
      "duration": 5.679,
      "text": "休憩入らずにもう喋る時にあの読み原稿"
    },
    {
      "start": 1148.039,
      "duration": 5.361,
      "text": "欲しいっていうことはあったと思います"
    },
    {
      "start": 1149.919,
      "duration": 6.64,
      "text": "うんただ事前にこの場に出てきて議会委"
    },
    {
      "start": 1153.4,
      "duration": 6.2,
      "text": "委員会でその内容がいいから悪いからまた"
    },
    {
      "start": 1156.559,
      "duration": 5.681,
      "text": "議事に半日入れないとかまそういうのは"
    },
    {
      "start": 1159.6,
      "duration": 5.559,
      "text": "あんまりやるべきじゃないかなと思うあの"
    },
    {
      "start": 1162.24,
      "duration": 5.88,
      "text": "多くのま膨張されてる方分からない来られ"
    },
    {
      "start": 1165.159,
      "duration": 5.601,
      "text": "てる方あれだけどこの主張報告自体も"
    },
    {
      "start": 1168.12,
      "duration": 7.039,
      "text": "みんな全部聞いてないんですよねだから"
    },
    {
      "start": 1170.76,
      "duration": 7.12,
      "text": "早くまずそれを早くあの世にあの示して"
    },
    {
      "start": 1175.159,
      "duration": 4.961,
      "text": "いただいてまその発言もしていただいてね"
    },
    {
      "start": 1177.88,
      "duration": 4.84,
      "text": "ただその発言ちゃんと聞き取るためにね"
    },
    {
      "start": 1180.12,
      "duration": 6.88,
      "text": "その後の質疑をちゃんと進めていくために"
    },
    {
      "start": 1182.72,
      "duration": 6.839,
      "text": "もその文章を事前に配って発言に入"
    },
    {
      "start": 1187.0,
      "duration": 5.799,
      "text": "るっていうことはこれは今までもやってき"
    },
    {
      "start": 1189.559,
      "duration": 5.521,
      "text": "たかなと思うんですけど委長その変動され"
    },
    {
      "start": 1192.799,
      "duration": 4.521,
      "text": "ますか今小林委が言われたのは市長発言の"
    },
    {
      "start": 1195.08,
      "duration": 4.8,
      "text": "前ということですが今回あの市長から言わ"
    },
    {
      "start": 1197.32,
      "duration": 4.44,
      "text": "れてのは市長発言の後ということでそれも"
    },
    {
      "start": 1199.88,
      "duration": 4.32,
      "text": "なおかつ昨日議長にお電話があって初めて"
    },
    {
      "start": 1201.76,
      "duration": 5.159,
      "text": "今日4社に図られたという状況でござい"
    },
    {
      "start": 1204.2,
      "duration": 6.28,
      "text": "ますので何を言うか分からないという中で"
    },
    {
      "start": 1206.919,
      "duration": 5.88,
      "text": "まそれをじゃ先にやってほしいということ"
    },
    {
      "start": 1210.48,
      "duration": 4.319,
      "text": "も含めてのご意見だったのかなという風に"
    },
    {
      "start": 1212.799,
      "duration": 7.0,
      "text": "思っております"
    },
    {
      "start": 1214.799,
      "duration": 7.441,
      "text": "はいかわかんないいや後ということあの"
    },
    {
      "start": 1219.799,
      "duration": 4.24,
      "text": "事前にその視聴報告の後に発言をさせて"
    },
    {
      "start": 1222.24,
      "duration": 3.36,
      "text": "くださいという申しではなかったと思って"
    },
    {
      "start": 1224.039,
      "duration": 5.281,
      "text": "ます"
    },
    {
      "start": 1225.6,
      "duration": 6.559,
      "text": "はいはいはい安"
    },
    {
      "start": 1229.32,
      "duration": 9.359,
      "text": "あの今回の視聴報告なんですけれどもこれ"
    },
    {
      "start": 1232.159,
      "duration": 10.201,
      "text": "はあの市長の公約を昼がす大変重要な内容"
    },
    {
      "start": 1238.679,
      "duration": 7.201,
      "text": "になってます私はそれを最初に書いた時に"
    },
    {
      "start": 1242.36,
      "duration": 6.64,
      "text": "市長はそこまでの重要な認識はなかっただ"
    },
    {
      "start": 1245.88,
      "duration": 6.88,
      "text": "けどこれまでのこれを公表した2月14日"
    },
    {
      "start": 1249.0,
      "duration": 7.48,
      "text": "に公表した後の様々な動きを見てえそれで"
    },
    {
      "start": 1252.76,
      "duration": 7.68,
      "text": "これはまずいと考えそして発言の機会をと"
    },
    {
      "start": 1256.48,
      "duration": 9.0,
      "text": "いう風にえ今求めているのではないかと"
    },
    {
      "start": 1260.44,
      "duration": 8.2,
      "text": "思いますこの視聴報告の中身が不十分だと"
    },
    {
      "start": 1265.48,
      "duration": 6.48,
      "text": "市長が感じているのではないですかこれは"
    },
    {
      "start": 1268.64,
      "duration": 3.32,
      "text": "書き直すべきだと思い"
    },
    {
      "start": 1272.279,
      "duration": 9.801,
      "text": "ますその後に発言したいその内容合わせて"
    },
    {
      "start": 1278.48,
      "duration": 6.48,
      "text": "示してください示すべきだと私は考えます"
    },
    {
      "start": 1282.08,
      "duration": 5.44,
      "text": "はいまあの主張報告と主張発言はちょっと"
    },
    {
      "start": 1284.96,
      "duration": 6.56,
      "text": "切り分けて考えていただきたいということ"
    },
    {
      "start": 1287.52,
      "duration": 8.44,
      "text": "ですねはいすいませんはい副議長はいあの"
    },
    {
      "start": 1291.52,
      "duration": 8.399,
      "text": "すいません今の総務部長の説明の中で総務"
    },
    {
      "start": 1295.96,
      "duration": 7.56,
      "text": "部長もその内容はご存知ないということな"
    },
    {
      "start": 1299.919,
      "duration": 6.841,
      "text": "わけですよね市長発言のでこの市長発言"
    },
    {
      "start": 1303.52,
      "duration": 7.44,
      "text": "っていうのは公式の場で発言されるわけ"
    },
    {
      "start": 1306.76,
      "duration": 9.2,
      "text": "ですからその行政内部での調整を図った上"
    },
    {
      "start": 1310.96,
      "duration": 7.959,
      "text": "での発言ではないということですかという"
    },
    {
      "start": 1315.96,
      "duration": 6.36,
      "text": "ことになるとこの発言というのはどいう"
    },
    {
      "start": 1318.919,
      "duration": 7.321,
      "text": "位置付けになるのかという風にお考えなの"
    },
    {
      "start": 1322.32,
      "duration": 7.68,
      "text": "かちょっとその辺りどこまで調整されて"
    },
    {
      "start": 1326.24,
      "duration": 5.76,
      "text": "市長が発言されるのかあのちょっと基準上"
    },
    {
      "start": 1330.0,
      "duration": 6.559,
      "text": "も聞いておいた方がいいかなと思いますの"
    },
    {
      "start": 1332.0,
      "duration": 7.2,
      "text": "でよろしくお願いいたしますはい総部長"
    },
    {
      "start": 1336.559,
      "duration": 5.441,
      "text": "はいあの今回視聴報告は優先整備路線の"
    },
    {
      "start": 1339.2,
      "duration": 5.52,
      "text": "検証日総合的判断についての視聴報告で"
    },
    {
      "start": 1342.0,
      "duration": 4.799,
      "text": "ございましてこの内容このえこうやって"
    },
    {
      "start": 1344.72,
      "duration": 5.4,
      "text": "議案としておまとめした内容につきまして"
    },
    {
      "start": 1346.799,
      "duration": 6.081,
      "text": "は議等に図って内で意思決定をしてると"
    },
    {
      "start": 1350.12,
      "duration": 5.72,
      "text": "いうことになりますえここで市長のご発言"
    },
    {
      "start": 1352.88,
      "duration": 5.88,
      "text": "につきましてはそれ以外のいういうことに"
    },
    {
      "start": 1355.84,
      "duration": 5.56,
      "text": "なりますが特にえ私は確認してございませ"
    },
    {
      "start": 1358.76,
      "duration": 5.6,
      "text": "んが特に政的なところでのご発言という"
    },
    {
      "start": 1361.4,
      "duration": 4.639,
      "text": "ことであればそれはあのこちらの方で確認"
    },
    {
      "start": 1364.36,
      "duration": 4.04,
      "text": "してるということにはならないということ"
    },
    {
      "start": 1366.039,
      "duration": 2.361,
      "text": "でござい"
    },
    {
      "start": 1368.559,
      "duration": 6.201,
      "text": "ます"
    },
    {
      "start": 1370.279,
      "duration": 6.961,
      "text": "はいまま内容は今誰も分からないという中"
    },
    {
      "start": 1374.76,
      "duration": 5.76,
      "text": "でま先ほどもし分からないということで仮"
    },
    {
      "start": 1377.24,
      "duration": 5.96,
      "text": "の話ですけれどものの視聴報告とま違う"
    },
    {
      "start": 1380.52,
      "duration": 4.399,
      "text": "ような中身あるいは先ほど副院長が指摘さ"
    },
    {
      "start": 1383.2,
      "duration": 5.359,
      "text": "れたようなことがもしあるとするのであれ"
    },
    {
      "start": 1384.919,
      "duration": 6.481,
      "text": "ばそれは前段の質疑の時間にも関わること"
    },
    {
      "start": 1388.559,
      "duration": 6.0,
      "text": "になると思いますのでであれば先に行う"
    },
    {
      "start": 1391.4,
      "duration": 5.36,
      "text": "べき明らかにしてから質疑に入られた方が"
    },
    {
      "start": 1394.559,
      "duration": 4.961,
      "text": "皆さんスムーズに質疑ができるのではない"
    },
    {
      "start": 1396.76,
      "duration": 4.6,
      "text": "かという風にも考えますけれどもまいずれ"
    },
    {
      "start": 1399.52,
      "duration": 4.44,
      "text": "にしてもその発言の内容が分からないので"
    },
    {
      "start": 1401.36,
      "duration": 5.04,
      "text": "今は雲を掴むような話でいいとも悪いとも"
    },
    {
      "start": 1403.96,
      "duration": 4.959,
      "text": "言えないま逆にそれを拒否するあれもない"
    },
    {
      "start": 1406.4,
      "duration": 5.12,
      "text": "ですけれどもはい今まそういう中で議会"
    },
    {
      "start": 1408.919,
      "duration": 4.921,
      "text": "委員会中か皆様ご意見ありますけれども"
    },
    {
      "start": 1411.52,
      "duration": 4.36,
      "text": "あのその主張報告の中身は明らかにして"
    },
    {
      "start": 1413.84,
      "duration": 4.8,
      "text": "いただきたいということについてはあ市長"
    },
    {
      "start": 1415.88,
      "duration": 4.12,
      "text": "発言ですね発言発言の中身に明らかにして"
    },
    {
      "start": 1418.64,
      "duration": 6.36,
      "text": "いただきたいということについてはいかが"
    },
    {
      "start": 1420.0,
      "duration": 7.279,
      "text": "ですかねはい伊谷委はいあの先ほど小林"
    },
    {
      "start": 1425.0,
      "duration": 4.159,
      "text": "委員の方からまご発言があた過去にまどう"
    },
    {
      "start": 1427.279,
      "duration": 4.361,
      "text": "いうことがあったかというところもご紹介"
    },
    {
      "start": 1429.159,
      "duration": 4.52,
      "text": "あったんですが私もそんなにあの長い経験"
    },
    {
      "start": 1431.64,
      "duration": 4.279,
      "text": "ではないのであんまりあのたくさんある"
    },
    {
      "start": 1433.679,
      "duration": 5.041,
      "text": "わけではないですけれどもま市長が報告"
    },
    {
      "start": 1435.919,
      "duration": 6.041,
      "text": "する中身について皆さんがしっかりあの"
    },
    {
      "start": 1438.72,
      "duration": 5.88,
      "text": "理解しながら聞くために事前にテキストを"
    },
    {
      "start": 1441.96,
      "duration": 6.12,
      "text": "あテキストていうか文章として文章を配布"
    },
    {
      "start": 1444.6,
      "duration": 6.6,
      "text": "した方がいいというようなあの思いは私も"
    },
    {
      "start": 1448.08,
      "duration": 5.56,
      "text": "あの今まで持っておりましたので今回も"
    },
    {
      "start": 1451.2,
      "duration": 5.12,
      "text": "市長が発言する前にまそれを配ってって"
    },
    {
      "start": 1453.64,
      "duration": 6.2,
      "text": "いうことはあのやるべきだと思いますただ"
    },
    {
      "start": 1456.32,
      "duration": 5.32,
      "text": "その中身について中身次第で発言事体を"
    },
    {
      "start": 1459.84,
      "duration": 3.76,
      "text": "あの許すとか許さないとかちょっとそう"
    },
    {
      "start": 1461.64,
      "duration": 5.519,
      "text": "いうのとは違うのかなという思いはして"
    },
    {
      "start": 1463.6,
      "duration": 6.319,
      "text": "おりますはいでまずその発言をペーパーで"
    },
    {
      "start": 1467.159,
      "duration": 5.361,
      "text": "出していただくということについては"
    },
    {
      "start": 1469.919,
      "duration": 5.401,
      "text": "え求めるということで皆さんよろしいです"
    },
    {
      "start": 1472.52,
      "duration": 2.8,
      "text": "かそこについて"
    },
    {
      "start": 1476.279,
      "duration": 7.64,
      "text": "はあはい"
    },
    {
      "start": 1478.72,
      "duration": 8.48,
      "text": "はいん本会議場会議場じゃないですよね"
    },
    {
      "start": 1483.919,
      "duration": 4.841,
      "text": "ただまそれも方は調整しね持ち帰れるね"
    },
    {
      "start": 1487.2,
      "duration": 4.68,
      "text": "配るか配らないか持ち帰らないとわから"
    },
    {
      "start": 1488.76,
      "duration": 7.56,
      "text": "ないですもんねはい配り方の方法はですね"
    },
    {
      "start": 1491.88,
      "duration": 7.0,
      "text": "前に調整しますまじゃあその配り方につい"
    },
    {
      "start": 1496.32,
      "duration": 8.56,
      "text": "てもあとるかどうかも含めてそれ市長のご"
    },
    {
      "start": 1498.88,
      "duration": 6.0,
      "text": "判断になると思いますのでうんはい"
    },
    {
      "start": 1506.399,
      "duration": 8.201,
      "text": "そはいはいどうぞ水上委員あの視聴報告"
    },
    {
      "start": 1511.159,
      "duration": 7.24,
      "text": "って結局今日視聴報告が終わればあのこの"
    },
    {
      "start": 1514.6,
      "duration": 5.88,
      "text": "内容に基づいて市長は東京都に要望書を"
    },
    {
      "start": 1518.399,
      "duration": 6.241,
      "text": "提出するっていう流れになってるわけです"
    },
    {
      "start": 1520.48,
      "duration": 7.64,
      "text": "ねで6団体の方からはあの今日要するに"
    },
    {
      "start": 1524.64,
      "duration": 6.639,
      "text": "その市民説明会をあのやってもらいたいっ"
    },
    {
      "start": 1528.12,
      "duration": 5.919,
      "text": "ていう要望書が出てますよねで政治的な"
    },
    {
      "start": 1531.279,
      "duration": 6.88,
      "text": "発言されるっていうんだけど中身分から"
    },
    {
      "start": 1534.039,
      "duration": 7.921,
      "text": "ないと僕ねわかんないですよね政治的なの"
    },
    {
      "start": 1538.159,
      "duration": 8.0,
      "text": "かどうかもでもあの要するにあの総務部長"
    },
    {
      "start": 1541.96,
      "duration": 6.24,
      "text": "は中身知らないわけだから全体あの部局と"
    },
    {
      "start": 1546.159,
      "duration": 4.481,
      "text": "しては確認してるわけでもないので多分"
    },
    {
      "start": 1548.2,
      "duration": 6.0,
      "text": "政治的な発言ではないかなと思われるん"
    },
    {
      "start": 1550.64,
      "duration": 6.96,
      "text": "ですねでね公約に関わる問題なんで何度も"
    },
    {
      "start": 1554.2,
      "duration": 7.079,
      "text": "言ってる通りで今までの市長方向とま違う"
    },
    {
      "start": 1557.6,
      "duration": 8.16,
      "text": "んですよあの立保育園の肺炎問題もねあの"
    },
    {
      "start": 1561.279,
      "duration": 6.961,
      "text": "ありましたけど今回ね公約を要するに昼"
    },
    {
      "start": 1565.76,
      "duration": 6.32,
      "text": "すってこと撤回するって中身になってる"
    },
    {
      "start": 1568.24,
      "duration": 7.08,
      "text": "わけだからあので市民に対するそのあの"
    },
    {
      "start": 1572.08,
      "duration": 7.44,
      "text": "言及があのほと丸切りないですよねこの中"
    },
    {
      "start": 1575.32,
      "duration": 7.64,
      "text": "にはあの要するに市民に対してその自らが"
    },
    {
      "start": 1579.52,
      "duration": 7.2,
      "text": "要するに公約を撤回することについてのま"
    },
    {
      "start": 1582.96,
      "duration": 6.4,
      "text": "謝罪もないし市民説明についても全くない"
    },
    {
      "start": 1586.72,
      "duration": 5.0,
      "text": "んですねまそういうで視聴報告に入って"
    },
    {
      "start": 1589.36,
      "duration": 5.48,
      "text": "いいのかっていうことを僕は冒頭から言っ"
    },
    {
      "start": 1591.72,
      "duration": 6.6,
      "text": "てるわけでそれがその視聴報告終わった後"
    },
    {
      "start": 1594.84,
      "duration": 6.16,
      "text": "になんか発言をしてで質疑に入っていくっ"
    },
    {
      "start": 1598.32,
      "duration": 5.599,
      "text": "ていう形になってくるとこれが終われば"
    },
    {
      "start": 1601.0,
      "duration": 5.72,
      "text": "もうねそのままあの東京都に要望書出すっ"
    },
    {
      "start": 1603.919,
      "duration": 6.0,
      "text": "ていう流れになるわけでしょそれが議会と"
    },
    {
      "start": 1606.72,
      "duration": 7.4,
      "text": "して本当にまいいのかどうか今まではだっ"
    },
    {
      "start": 1609.919,
      "duration": 6.441,
      "text": "てあの市民が理解しないあの道路は作らせ"
    },
    {
      "start": 1614.12,
      "duration": 5.439,
      "text": "ないっていうま全市長の立場があったわけ"
    },
    {
      "start": 1616.36,
      "duration": 6.52,
      "text": "だから市民合意っていうのをその大事にし"
    },
    {
      "start": 1619.559,
      "duration": 6.12,
      "text": "てきたと思うんですよで議会はあの要する"
    },
    {
      "start": 1622.88,
      "duration": 6.36,
      "text": "にま前回1ではなかったけれどもいろんな"
    },
    {
      "start": 1625.679,
      "duration": 6.761,
      "text": "意見書も出してきましたまそういう経過も"
    },
    {
      "start": 1629.24,
      "duration": 6.36,
      "text": "ある中でですねこれを要するに主張報告"
    },
    {
      "start": 1632.44,
      "duration": 6.16,
      "text": "あので市長発言あどうぞやってください"
    },
    {
      "start": 1635.6,
      "duration": 5.24,
      "text": "みたいな形であの進めてていいのかって"
    },
    {
      "start": 1638.6,
      "duration": 4.84,
      "text": "ことなんですよこれが終わればだってもう"
    },
    {
      "start": 1640.84,
      "duration": 5.319,
      "text": "そのまま要望者が出てくっていう話になる"
    },
    {
      "start": 1643.44,
      "duration": 6.8,
      "text": "わけでしょ市民に説明しなくて要望書出し"
    },
    {
      "start": 1646.159,
      "duration": 7.841,
      "text": "ていいんですかね市民にことも詫びもなく"
    },
    {
      "start": 1650.24,
      "duration": 6.12,
      "text": "あのこの要するに公約撤回しますって話を"
    },
    {
      "start": 1654.0,
      "duration": 5.44,
      "text": "あのやっていいんですかねそういうことを"
    },
    {
      "start": 1656.36,
      "duration": 6.64,
      "text": "議会として認めるのかどうかっていう話だ"
    },
    {
      "start": 1659.44,
      "duration": 7.119,
      "text": "と思うんですよだから今回はね慰霊の時代"
    },
    {
      "start": 1663.0,
      "duration": 6.279,
      "text": "なんですよこの市長報告がだから総務部長"
    },
    {
      "start": 1666.559,
      "duration": 6.12,
      "text": "も全く何も知らないんだったら市長に聞い"
    },
    {
      "start": 1669.279,
      "duration": 6.321,
      "text": "て確認してもらいたいんですよどういう"
    },
    {
      "start": 1672.679,
      "duration": 6.48,
      "text": "中身なのかもし謝罪するっていうんだっ"
    },
    {
      "start": 1675.6,
      "duration": 6.76,
      "text": "たらどういう謝罪なのかあのあのはっきり"
    },
    {
      "start": 1679.159,
      "duration": 6.841,
      "text": "させてもらわないと主張報告終わった後に"
    },
    {
      "start": 1682.36,
      "duration": 6.919,
      "text": "発言するわけですよ主張報告がされたって"
    },
    {
      "start": 1686.0,
      "duration": 6.84,
      "text": "いう規定技術の上に発言されるって形に"
    },
    {
      "start": 1689.279,
      "duration": 6.12,
      "text": "なってしまうのであのそれはやっぱりね僕"
    },
    {
      "start": 1692.84,
      "duration": 6.64,
      "text": "どういう発言されるかわかんないけれども"
    },
    {
      "start": 1695.399,
      "duration": 6.52,
      "text": "あの主張発言あのあの報告のあの総合的"
    },
    {
      "start": 1699.48,
      "duration": 5.12,
      "text": "判断が覆るっていうことには全くならない"
    },
    {
      "start": 1701.919,
      "duration": 5.201,
      "text": "んだろうなっていう風には僕はあの報告さ"
    },
    {
      "start": 1704.6,
      "duration": 4.76,
      "text": "れてるわけだから思うわけでそういうこと"
    },
    {
      "start": 1707.12,
      "duration": 5.84,
      "text": "で言ってるんですよだからそういうことと"
    },
    {
      "start": 1709.36,
      "duration": 6.159,
      "text": "して是非ね議会の皆さん義軍の皆さんもね"
    },
    {
      "start": 1712.96,
      "duration": 6.64,
      "text": "あの事前にま議運でとりあえず確認するっ"
    },
    {
      "start": 1715.519,
      "duration": 8.04,
      "text": "てこだけでもいいですけどあのそれはね"
    },
    {
      "start": 1719.6,
      "duration": 6.76,
      "text": "少なくともやって入っていかないとあの"
    },
    {
      "start": 1723.559,
      "duration": 6.041,
      "text": "このまま要するに視聴報告終わりましたと"
    },
    {
      "start": 1726.36,
      "duration": 6.12,
      "text": "じゃあ東京都に行きますとあの市民説明会"
    },
    {
      "start": 1729.6,
      "duration": 4.4,
      "text": "じゃあ検討しますとかねあの謝罪について"
    },
    {
      "start": 1732.48,
      "duration": 3.96,
      "text": "もなんかはっきりしないまま終われ"
    },
    {
      "start": 1734.0,
      "duration": 5.48,
      "text": "るってことになっていいのかっていうこと"
    },
    {
      "start": 1736.44,
      "duration": 6.4,
      "text": "なので是非ね皆さんよくご検討いただき"
    },
    {
      "start": 1739.48,
      "duration": 6.12,
      "text": "たいな私はだからあの遭遇長から確認して"
    },
    {
      "start": 1742.84,
      "duration": 5.88,
      "text": "もらっ市長にどういう発言なのかっていう"
    },
    {
      "start": 1745.6,
      "duration": 6.24,
      "text": "ことについてはあの少なくとも議運の"
    },
    {
      "start": 1748.72,
      "duration": 5.319,
      "text": "メンバーにはあのこの場にははっきり示し"
    },
    {
      "start": 1751.84,
      "duration": 4.04,
      "text": "ていただきたいということを再度あの求め"
    },
    {
      "start": 1754.039,
      "duration": 3.321,
      "text": "ておきたいと思いますはいあのご視聴の点"
    },
    {
      "start": 1755.88,
      "duration": 4.039,
      "text": "についてはちょっとあの質疑の方でやって"
    },
    {
      "start": 1757.36,
      "duration": 5.159,
      "text": "いただければという風にはいはい思います"
    },
    {
      "start": 1759.919,
      "duration": 5.401,
      "text": "んではいあの森戸副議長はいちょっと今"
    },
    {
      "start": 1762.519,
      "duration": 6.441,
      "text": "あの私もずっと考えてたんですが総務部長"
    },
    {
      "start": 1765.32,
      "duration": 6.12,
      "text": "からま政治的な発言だって"
    },
    {
      "start": 1768.96,
      "duration": 7.36,
      "text": "あそうだごめんなさい政治あごめんなさい"
    },
    {
      "start": 1771.44,
      "duration": 7.839,
      "text": "ねえっと政治的な発言だということをとは"
    },
    {
      "start": 1776.32,
      "duration": 5.599,
      "text": "言ってないいやなんとなくもこもことそう"
    },
    {
      "start": 1779.279,
      "duration": 6.361,
      "text": "おっしゃったかなと思うんですがただね"
    },
    {
      "start": 1781.919,
      "duration": 6.88,
      "text": "やっぱり議会で発言されるっていうことの"
    },
    {
      "start": 1785.64,
      "duration": 8.159,
      "text": "重みを考えていただきたいなと市長はで"
    },
    {
      "start": 1788.799,
      "duration": 8.561,
      "text": "このその市長発言が部局も知らない何を"
    },
    {
      "start": 1793.799,
      "duration": 6.841,
      "text": "言われるか知らないで突然ですね市長が"
    },
    {
      "start": 1797.36,
      "duration": 8.52,
      "text": "発言をされるっていうことはですね私たち"
    },
    {
      "start": 1800.64,
      "duration": 10.919,
      "text": "議会側としてはですねこれはあの議長の"
    },
    {
      "start": 1805.88,
      "duration": 9.84,
      "text": "個人的な発言であって行政あ市長の市長の"
    },
    {
      "start": 1811.559,
      "duration": 7.681,
      "text": "個人的な発言であってそのなんて言うん"
    },
    {
      "start": 1815.72,
      "duration": 6.799,
      "text": "ですかね行政との関わりはないんだこんな"
    },
    {
      "start": 1819.24,
      "duration": 6.72,
      "text": "ことはありえないんですよだから主張発言"
    },
    {
      "start": 1822.519,
      "duration": 6.921,
      "text": "をされるにあたってはま極なりきちっと"
    },
    {
      "start": 1825.96,
      "duration": 4.839,
      "text": "調整された上で発言をいただかないとです"
    },
    {
      "start": 1829.44,
      "duration": 6.52,
      "text": "ね"
    },
    {
      "start": 1830.799,
      "duration": 9.321,
      "text": "あの議会としては極めて軽んじられてると"
    },
    {
      "start": 1835.96,
      "duration": 6.36,
      "text": "その市長発言の重みについてですね市長"
    },
    {
      "start": 1840.12,
      "duration": 6.2,
      "text": "自身がお分かりになってないんじゃないか"
    },
    {
      "start": 1842.32,
      "duration": 7.68,
      "text": "と言わざる終えずあのただ配"
    },
    {
      "start": 1846.32,
      "duration": 7.52,
      "text": "るっていうことだけではなくきちっと部局"
    },
    {
      "start": 1850.0,
      "duration": 7.279,
      "text": "なりえ町内全体のですね確認を取った上で"
    },
    {
      "start": 1853.84,
      "duration": 6.28,
      "text": "の発言にしていただきたいとそうじゃ"
    },
    {
      "start": 1857.279,
      "duration": 3.801,
      "text": "なきゃねおかしいですよこれは議会は変じ"
    },
    {
      "start": 1860.12,
      "duration": 3.399,
      "text": "られて"
    },
    {
      "start": 1861.08,
      "duration": 5.24,
      "text": "るってことですよそのことをよく踏まえて"
    },
    {
      "start": 1863.519,
      "duration": 5.601,
      "text": "ですね私たちも対応する必要があるんじゃ"
    },
    {
      "start": 1866.32,
      "duration": 5.239,
      "text": "ないかということを委員長にも申し上げて"
    },
    {
      "start": 1869.12,
      "duration": 4.96,
      "text": "おきたいと思いますはいま様々ご意見は"
    },
    {
      "start": 1871.559,
      "duration": 5.161,
      "text": "いだいたところでございますがまずはその"
    },
    {
      "start": 1874.08,
      "duration": 4.24,
      "text": "発言をペーパーとして出せるのかどうかで"
    },
    {
      "start": 1876.72,
      "duration": 3.919,
      "text": "えそれが出せるということであればどう"
    },
    {
      "start": 1878.32,
      "duration": 4.52,
      "text": "いう形で出すのかということについてまず"
    },
    {
      "start": 1880.639,
      "duration": 5.601,
      "text": "ちょっと総務部長の方から今のご意見とも"
    },
    {
      "start": 1882.84,
      "duration": 6.439,
      "text": "踏まえた上で市長にお聞きをいただきたい"
    },
    {
      "start": 1886.24,
      "duration": 4.919,
      "text": "ということでちょっと1回議会会は休憩を"
    },
    {
      "start": 1889.279,
      "duration": 3.201,
      "text": "させていただいて1回市長にお持ち帰り"
    },
    {
      "start": 1891.159,
      "duration": 3.48,
      "text": "いただきたいと思いますがそれでよろしい"
    },
    {
      "start": 1892.48,
      "duration": 6.0,
      "text": "ですか皆さん1回はいはいではそういった"
    },
    {
      "start": 1894.639,
      "duration": 6.361,
      "text": "ことではい務長よろしいですかあ別にはい"
    },
    {
      "start": 1898.48,
      "duration": 4.199,
      "text": "はい総務長えあの議会でえそういうのその"
    },
    {
      "start": 1901.0,
      "duration": 3.559,
      "text": "ような表目があったということでまずは"
    },
    {
      "start": 1902.679,
      "duration": 6.761,
      "text": "市長にご報告させていただきたいと思い"
    },
    {
      "start": 1904.559,
      "duration": 4.881,
      "text": "ますはいそれでは一旦休憩いたします"
    }
  ]
}