{
  "entries": [
    {
      "start": 50.879,
      "duration": 3.0,
      "text": "じゃあ、お疲れ様です。議会運営委員会協議会始めます。"
    },
    {
      "start": 54.199,
      "duration": 6.2,
      "text": "お手元の協議事項を見ていただいて、えっ"
    },
    {
      "start": 57.359,
      "duration": 6.88,
      "text": "と、協議事項の1番、え、保留案件保留"
    },
    {
      "start": 60.399,
      "duration": 7.161,
      "text": "事項の確認について、えっと、本日の進興"
    },
    {
      "start": 64.239,
      "duration": 6.2,
      "text": "予定についてもいいのかな?じゃ、局長。"
    },
    {
      "start": 67.56,
      "duration": 5.599,
      "text": "はい。え、それでは進興予定表をご覧"
    },
    {
      "start": 70.439,
      "duration": 6.121,
      "text": "いただきたいと思います。え、1番の議会"
    },
    {
      "start": 73.159,
      "duration": 6.801,
      "text": "運営委員会を美協議会につきましては今の"
    },
    {
      "start": 76.56,
      "duration": 6.36,
      "text": "状況でございます。え、2番で建設環境"
    },
    {
      "start": 79.96,
      "duration": 6.36,
      "text": "委員会でございますが、保留案件、保留"
    },
    {
      "start": 82.92,
      "duration": 6.839,
      "text": "事項が2件ございますので、この審査、え"
    },
    {
      "start": 86.32,
      "duration": 9.4,
      "text": "、その後、え、3番の厚生文教委員会で、"
    },
    {
      "start": 89.759,
      "duration": 9.521,
      "text": "え、1のか1から利面の、えっと、右側か"
    },
    {
      "start": 95.72,
      "duration": 6.84,
      "text": "58及びその他の2まで、え、の審査に"
    },
    {
      "start": 99.28,
      "duration": 7.119,
      "text": "なりまして、え、その後、え、4番の会派"
    },
    {
      "start": 102.56,
      "duration": 5.159,
      "text": "代表者会議、え、5番の議会運営委員会で"
    },
    {
      "start": 106.399,
      "duration": 4.32,
      "text": "本日の進興"
    },
    {
      "start": 107.719,
      "duration": 3.0,
      "text": "の確認と議会整理便についての確認をだくというのが"
    },
    {
      "start": 111.799,
      "duration": 3.201,
      "text": "1"
    },
    {
      "start": 112.0,
      "duration": 4.24,
      "text": "日の流れになってございます。以上です。"
    },
    {
      "start": 115.0,
      "duration": 4.24,
      "text": "はい。"
    },
    {
      "start": 116.24,
      "duration": 3.0,
      "text": "えっとということなんですけど、開代表者会議が"
    },
    {
      "start": 119.399,
      "duration": 3.241,
      "text": "4"
    },
    {
      "start": 119.64,
      "duration": 3.0,
      "text": "番に入ってるんですけど、ここをどこに入れるのかっていうことで、ちょっと議長の方からご提案ありますでしょうか?"
    },
    {
      "start": 125.92,
      "duration": 3.16,
      "text": "あ、協議会です。協議会です。"
    },
    {
      "start": 128.08,
      "duration": 3.879,
      "text": "委員長、"
    },
    {
      "start": 129.08,
      "duration": 3.08,
      "text": "えっと、ま、おそらく"
    },
    {
      "start": 131.959,
      "duration": 2.181,
      "text": "3"
    },
    {
      "start": 132.16,
      "duration": 5.52,
      "text": "時半の段階で、えっと、公分が終わってればまた別な話なんですが、えっと、ま、見込みとすれば、えっと、配が入るか分からないというのは、あの、皆さんもちょっと、ま、不便じゃないかなと思うんで、"
    },
    {
      "start": 134.14,
      "duration": 3.54,
      "text": "[音楽]"
    },
    {
      "start": 148.319,
      "duration": 4.681,
      "text": "3時半しくは5"
    },
    {
      "start": 150.0,
      "duration": 3.0,
      "text": "時半、え、その辺の霧りのいいところで、え、派を入れて、え、条例決議"
    },
    {
      "start": 157.4,
      "duration": 3.0,
      "text": "のね、あの、確認をしていただきたいという風に思うんですが、え、"
    },
    {
      "start": 161.879,
      "duration": 3.881,
      "text": "3時半がいいか5"
    },
    {
      "start": 162.76,
      "duration": 3.0,
      "text": "時半がいいか皆さんで決めていただければと思います。"
    },
    {
      "start": 166.72,
      "duration": 3.0,
      "text": "ということなんですが、皆さんいかがですか?"
    },
    {
      "start": 173.239,
      "duration": 3.161,
      "text": "3"
    },
    {
      "start": 173.4,
      "duration": 3.0,
      "text": "時半ですかという意見が体制の"
    },
    {
      "start": 177.239,
      "duration": 3.121,
      "text": "5時半って方いらっしゃいます。"
    },
    {
      "start": 182.239,
      "duration": 4.36,
      "text": "うん。じゃあ3時半します。"
    },
    {
      "start": 184.48,
      "duration": 2.64,
      "text": "じゃあ3時半。"
    },
    {
      "start": 186.599,
      "duration": 3.521,
      "text": "39"
    },
    {
      "start": 187.12,
      "duration": 3.0,
      "text": "件終わった後って形になのかな。開になると。"
    },
    {
      "start": 190.599,
      "duration": 2.801,
      "text": "はい。"
    },
    {
      "start": 191.239,
      "duration": 2.881,
      "text": "で、運は1番最後に"
    },
    {
      "start": 193.4,
      "duration": 3.72,
      "text": "はい。"
    },
    {
      "start": 194.12,
      "duration": 3.0,
      "text": "進行確認がありますのでよろしくお願いします。で、あとその運のね、えっと、閉中日程なんですけど"
    },
    {
      "start": 202.959,
      "duration": 4.481,
      "text": "10月31月"
    },
    {
      "start": 206.56,
      "duration": 3.88,
      "text": "1417"
    },
    {
      "start": 207.44,
      "duration": 3.0,
      "text": "っていう提案したんですが、どれもね、それぞれ皆さん予定が入っていて難しいと。"
    },
    {
      "start": 213.159,
      "duration": 8.041,
      "text": "で、17日はあの入れられないことはない"
    },
    {
      "start": 217.2,
      "duration": 7.16,
      "text": "んですけど、三宅島が16日まであって、"
    },
    {
      "start": 221.2,
      "duration": 5.119,
      "text": "あの天候の関係であの場合によって戻って"
    },
    {
      "start": 224.36,
      "duration": 7.2,
      "text": "これないっていう可能性もないわけではな"
    },
    {
      "start": 226.319,
      "duration": 8.401,
      "text": "いってことと三宅の視察が終わ企画"
    },
    {
      "start": 231.56,
      "duration": 5.92,
      "text": "の施が始まるっていうこともあって"
    },
    {
      "start": 234.72,
      "duration": 7.76,
      "text": "総務企画の皆さん大変かなっていうのも"
    },
    {
      "start": 237.48,
      "duration": 7.959,
      "text": "あるので10月の17日金曜日"
    },
    {
      "start": 242.48,
      "duration": 8.16,
      "text": "ちょ早いんであまり提案はしてなかったん"
    },
    {
      "start": 245.439,
      "duration": 8.64,
      "text": "ですよ。あの17日金曜日でちょっとここ"
    },
    {
      "start": 250.64,
      "duration": 6.64,
      "text": "しか入れられないんですね。それか17に"
    },
    {
      "start": 254.079,
      "duration": 7.041,
      "text": "無理やり入れるのか。あとは3日前の議会"
    },
    {
      "start": 257.28,
      "duration": 7.44,
      "text": "運営委員会であの全て協議しなんていう"
    },
    {
      "start": 261.12,
      "duration": 7.48,
      "text": "閉会中のものもやっちゃうみたいなそんな"
    },
    {
      "start": 264.72,
      "duration": 8.52,
      "text": "感じなんですが"
    },
    {
      "start": 268.6,
      "duration": 7.64,
      "text": "で17日になるとあの協議報告書を定例"
    },
    {
      "start": 273.24,
      "duration": 6.64,
      "text": "会中に出してもらうことになるんですけど"
    },
    {
      "start": 276.24,
      "duration": 7.2,
      "text": "今回協議報告書ってあのあまり議論して"
    },
    {
      "start": 279.88,
      "duration": 5.68,
      "text": "ないので出すものは特にないかなと思うの"
    },
    {
      "start": 283.44,
      "duration": 4.319,
      "text": "で無理して出さなくてもいいって"
    },
    {
      "start": 285.56,
      "duration": 2.68,
      "text": "っていう確認が取れれば"
    },
    {
      "start": 287.759,
      "duration": 3.481,
      "text": "17"
    },
    {
      "start": 288.24,
      "duration": 3.0,
      "text": "日でもあ、出せるところは出してもらうって感じ。あ、すいません。いいです。ちょっとあ、"
    },
    {
      "start": 295.72,
      "duration": 3.0,
      "text": "今決めなくていいです。あのあ、いいです。いいです。議長あの最後のところで"
    },
    {
      "start": 301.12,
      "duration": 3.799,
      "text": "うん。"
    },
    {
      "start": 301.919,
      "duration": 3.0,
      "text": "最後最後かまた疑まで決めればいいということなので、あの、そこまででちょっと"
    },
    {
      "start": 310.199,
      "duration": 5.84,
      "text": "だから10月17日金曜日か"
    },
    {
      "start": 314.199,
      "duration": 4.84,
      "text": "10月11月17"
    },
    {
      "start": 316.039,
      "duration": 3.0,
      "text": "日月曜日に入れるのかあとはえっと"
    },
    {
      "start": 320.12,
      "duration": 3.519,
      "text": "11月25日のえっと第"
    },
    {
      "start": 323.44,
      "duration": 3.199,
      "text": "4"
    },
    {
      "start": 323.639,
      "duration": 3.0,
      "text": "回定例会の前の議会運営委員会と一緒にやるのかどうかというあの"
    },
    {
      "start": 329.72,
      "duration": 4.479,
      "text": "3つの選択しかない"
    },
    {
      "start": 331.199,
      "duration": 3.0,
      "text": "ということですので、是非お持ち帰りただきたいと思います。えっと、その他何かありますか?皆さんから特にいいですか?はい。"
    },
    {
      "start": 340.88,
      "duration": 3.0,
      "text": "じゃあ以上でいいですか?じゃあ以上で議会委員会終わります。お疲れ様です。"
    },
    {
      "start": 376.919,
      "duration": 3.0,
      "text": "は"
    }
  ]
}